bactn_qt_template-1.0.1.dist-info/licenses/LICENSE
qtcommandstemplate/__init__.py
qtcommandstemplate/thonny_plugin.py
bactn_qt_template-1.0.1.dist-info/METADATA
bactn_qt_template-1.0.1.dist-info/WHEEL
bactn_qt_template-1.0.1.dist-info/entry_points.txt
bactn_qt_template-1.0.1.dist-info/top_level.txt
bactn_qt_template-1.0.1.dist-info/RECORD
