Metadata-Version: 2.4
Name: bactn-qt-template
Version: 1.0.1
Summary: A Thonny plugin to quickly insert a PyQt5 application template. Designed especially for Tunisian Bac students to make practicing Qt easier during exam prep. Some schools already use helpful tools like this — I hope it supports your learning too. Wishing you the best of luck in your finals (or any project you're working on)! Feel free to share with friends — and keep going, you're doing great! :3
Author-email: nex <kenotheos1@gmail.com>
License: MIT
Classifier: Programming Language :: Python :: 3
Classifier: License :: OSI Approved :: MIT License
Classifier: Operating System :: OS Independent
Requires-Python: >=3.7
License-File: LICENSE
Dynamic: license-file
